[
    {
        "id": 1462961,
        "propertyId": 162487260,
        "recordingDate": "2026-01-09",
        "buyerName": "JOHN L YEE TRUST",
        "formattedBuyerName": "john-l-yee-trust9c66bb014e88ba2ffad806cf711fc518",
        "lenderName": null,
        "address": "3320-22 HORTON AVE # 22",
        "phone": null,
        "city": "SAN DIEGO",
        "zipCode": "92103",
        "buildingArea": 2924,
        "yearBuilt": null,
        "avmValue": 2577285,
        "saleValue": 1011000,
        "saleDate": "2026-01-06",
        "sellerName": "3MT3 INC",
        "latitude": 32.739506,
        "longitude": -117.173757,
        "isCorporate": false,
        "isDiscountedPurchase": false,
        "isCashBuyer": true,
        "isPrivateLender": false,
        "bedrooms": 4,
        "bathrooms": 4,
        "propertyType": "Single Family Residential",
        "msa": "San Diego-Chula Vista-Carlsbad, CA",
        "state": "CA",
        "loanAmount": 0,
        "buyerPropertiesCount": 2,
        "buyerTransactionsCount": 2,
        "hasProfilePage": false,
        "exitDate": null,
        "exitValue": null,
        "exitBuyerName": null,
        "profitLoss": null,
        "holdDays": null
    },
    {
        "id": 1657807,
        "propertyId": 157813952,
        "recordingDate": "2026-01-09",
        "buyerName": "Opendoor",
        "formattedBuyerName": "opendoor",
        "lenderName": null,
        "address": "1881 OLIVIA ST",
        "phone": null,
        "city": "EL CAJON",
        "zipCode": "92021",
        "buildingArea": 1504,
        "yearBuilt": 2019,
        "avmValue": 842909,
        "saleValue": 708500,
        "saleDate": "2026-01-08",
        "sellerName": "BENSON LASHAWN",
        "latitude": 32.817329,
        "longitude": -116.91279,
        "isCorporate": true,
        "isDiscountedPurchase": true,
        "isCashBuyer": true,
        "isPrivateLender": false,
        "bedrooms": 3,
        "bathrooms": 2,
        "propertyType": "Single Family Residential",
        "msa": "San Diego-Chula Vista-Carlsbad, CA",
        "state": "CA",
        "loanAmount": 0,
        "buyerPropertiesCount": 3898,
        "buyerTransactionsCount": 64103,
        "hasProfilePage": true,
        "exitDate": null,
        "exitValue": null,
        "exitBuyerName": null,
        "profitLoss": null,
        "holdDays": null
    },
    {
        "id": 10669177,
        "propertyId": 18447592,
        "recordingDate": "2026-01-09",
        "buyerName": "MCCLOY IRREVOCABLE HOME TRUST",
        "formattedBuyerName": "mccloy-irrevocable-home-trust98c937b55fe1f79b6f4d2b85433c5ed2",
        "lenderName": null,
        "address": "358 VIA METATES",
        "phone": null,
        "city": "OCEANSIDE",
        "zipCode": "92057",
        "buildingArea": 1290,
        "yearBuilt": 1988,
        "avmValue": 997369,
        "saleValue": 1028000,
        "saleDate": "2026-01-06",
        "sellerName": "ERWIN LUKE",
        "latitude": 33.244994,
        "longitude": -117.288965,
        "isCorporate": false,
        "isDiscountedPurchase": false,
        "isCashBuyer": true,
        "isPrivateLender": false,
        "bedrooms": 3,
        "bathrooms": 2,
        "propertyType": "Single Family Residential",
        "msa": "San Diego-Chula Vista-Carlsbad, CA",
        "state": "CA",
        "loanAmount": 0,
        "buyerPropertiesCount": 1,
        "buyerTransactionsCount": 1,
        "hasProfilePage": false,
        "exitDate": null,
        "exitValue": null,
        "exitBuyerName": null,
        "profitLoss": null,
        "holdDays": null
    },
    {
        "id": 10667054,
        "propertyId": 18490268,
        "recordingDate": "2026-01-09",
        "buyerName": "LEMON LTD",
        "formattedBuyerName": "lemon-ltd-ca",
        "lenderName": null,
        "address": "1401 S PACIFIC ST UNIT 103",
        "phone": null,
        "city": "OCEANSIDE",
        "zipCode": "92054",
        "buildingArea": 1224,
        "yearBuilt": 1977,
        "avmValue": 1063671,
        "saleValue": 99000,
        "saleDate": "2026-01-06",
        "sellerName": "BAUMGARTNER JOSEPH MATTHEW",
        "latitude": 33.178798,
        "longitude": -117.370765,
        "isCorporate": true,
        "isDiscountedPurchase": false,
        "isCashBuyer": true,
        "isPrivateLender": false,
        "bedrooms": 1,
        "bathrooms": 2,
        "propertyType": "Condo",
        "msa": "San Diego-Chula Vista-Carlsbad, CA",
        "state": "CA",
        "loanAmount": 0,
        "buyerPropertiesCount": 1,
        "buyerTransactionsCount": 1,
        "hasProfilePage": false,
        "exitDate": null,
        "exitValue": null,
        "exitBuyerName": null,
        "profitLoss": null,
        "holdDays": null
    },
    {
        "id": 10663215,
        "propertyId": 18609843,
        "recordingDate": "2026-01-09",
        "buyerName": "KOVACH STEVEN LEE",
        "formattedBuyerName": "kovach-steven-leee7c206be974c56302eb20904945c9971",
        "lenderName": null,
        "address": "2298 LINDSAY DR",
        "phone": null,
        "city": "CARLSBAD",
        "zipCode": "92008",
        "buildingArea": 1440,
        "yearBuilt": 1985,
        "avmValue": 606683,
        "saleValue": 599000,
        "saleDate": "2026-01-06",
        "sellerName": "RSDCO LLC",
        "latitude": 33.14279,
        "longitude": -117.287512,
        "isCorporate": false,
        "isDiscountedPurchase": false,
        "isCashBuyer": true,
        "isPrivateLender": false,
        "bedrooms": 2,
        "bathrooms": 2,
        "propertyType": null,
        "msa": "San Diego-Chula Vista-Carlsbad, CA",
        "state": "CA",
        "loanAmount": 0,
        "buyerPropertiesCount": 1,
        "buyerTransactionsCount": 1,
        "hasProfilePage": false,
        "exitDate": null,
        "exitValue": null,
        "exitBuyerName": null,
        "profitLoss": null,
        "holdDays": null
    },
    {
        "id": 10661528,
        "propertyId": 18668556,
        "recordingDate": "2026-01-09",
        "buyerName": "KREAMER FAMILY LIVING TRUST",
        "formattedBuyerName": "kreamer-family-living-trust300f4540630b683baf20f7e1d9ea338a",
        "lenderName": null,
        "address": "12880 CIRCULO DARDO",
        "phone": null,
        "city": "SAN DIEGO",
        "zipCode": "92128",
        "buildingArea": 1565,
        "yearBuilt": 1979,
        "avmValue": 1138268,
        "saleValue": 1110000,
        "saleDate": "2026-01-06",
        "sellerName": "DBZ CAPITAL VENTURES LLC",
        "latitude": 33.037487,
        "longitude": -117.05127,
        "isCorporate": false,
        "isDiscountedPurchase": false,
        "isCashBuyer": true,
        "isPrivateLender": false,
        "bedrooms": 3,
        "bathrooms": 2,
        "propertyType": "Condo",
        "msa": "San Diego-Chula Vista-Carlsbad, CA",
        "state": "CA",
        "loanAmount": 0,
        "buyerPropertiesCount": 1,
        "buyerTransactionsCount": 1,
        "hasProfilePage": false,
        "exitDate": null,
        "exitValue": null,
        "exitBuyerName": null,
        "profitLoss": null,
        "holdDays": null
    },
    {
        "id": 10660917,
        "propertyId": 18684381,
        "recordingDate": "2026-01-09",
        "buyerName": "LIVING LEGACY HOMES INC",
        "formattedBuyerName": "living-legacy-homes-inc-ca",
        "lenderName": null,
        "address": "603 BEVERLY PL",
        "phone": null,
        "city": "SAN MARCOS",
        "zipCode": "92078",
        "buildingArea": 1068,
        "yearBuilt": 1984,
        "avmValue": 512199,
        "saleValue": 353101,
        "saleDate": "2026-01-07",
        "sellerName": "TRUSTEE CORPS",
        "latitude": 33.134261,
        "longitude": -117.203206,
        "isCorporate": true,
        "isDiscountedPurchase": true,
        "isCashBuyer": true,
        "isPrivateLender": false,
        "bedrooms": 2,
        "bathrooms": 1,
        "propertyType": "Condo",
        "msa": "San Diego-Chula Vista-Carlsbad, CA",
        "state": "CA",
        "loanAmount": 0,
        "buyerPropertiesCount": 1,
        "buyerTransactionsCount": 2,
        "hasProfilePage": true,
        "exitDate": null,
        "exitValue": null,
        "exitBuyerName": null,
        "profitLoss": null,
        "holdDays": null
    },
    {
        "id": 10659480,
        "propertyId": 18717537,
        "recordingDate": "2026-01-09",
        "buyerName": "DARUGAR ALI A",
        "formattedBuyerName": "darugar-ali-afab8b8451f0c03cc56003f6c0c630dc2",
        "lenderName": null,
        "address": "875 LA MIRADA AVE",
        "phone": null,
        "city": "ENCINITAS",
        "zipCode": "92024",
        "buildingArea": 726,
        "yearBuilt": 1947,
        "avmValue": 742094,
        "saleValue": 1350000,
        "saleDate": "2026-01-08",
        "sellerName": "GARCIA GILDARDO",
        "latitude": 33.064659,
        "longitude": -117.288137,
        "isCorporate": false,
        "isDiscountedPurchase": false,
        "isCashBuyer": true,
        "isPrivateLender": false,
        "bedrooms": 2,
        "bathrooms": 1,
        "propertyType": "Single Family Residential",
        "msa": "San Diego-Chula Vista-Carlsbad, CA",
        "state": "CA",
        "loanAmount": 0,
        "buyerPropertiesCount": 1,
        "buyerTransactionsCount": 1,
        "hasProfilePage": false,
        "exitDate": null,
        "exitValue": null,
        "exitBuyerName": null,
        "profitLoss": null,
        "holdDays": null
    },
    {
        "id": 10655825,
        "propertyId": 18806718,
        "recordingDate": "2026-01-09",
        "buyerName": "PAULSON KERRY G",
        "formattedBuyerName": "paulson-kerry-gaba12a884e2da122225ad8e5ebf5ccdc",
        "lenderName": null,
        "address": "407 VIA ULTIMO",
        "phone": null,
        "city": "ENCINITAS",
        "zipCode": "92024",
        "buildingArea": 2336,
        "yearBuilt": 1987,
        "avmValue": 1930733,
        "saleValue": 2000000,
        "saleDate": "2026-01-06",
        "sellerName": "SALAMA INVESTMENT LLC",
        "latitude": 33.053177,
        "longitude": -117.267144,
        "isCorporate": false,
        "isDiscountedPurchase": false,
        "isCashBuyer": true,
        "isPrivateLender": false,
        "bedrooms": 5,
        "bathrooms": 3,
        "propertyType": "Single Family Residential",
        "msa": "San Diego-Chula Vista-Carlsbad, CA",
        "state": "CA",
        "loanAmount": 0,
        "buyerPropertiesCount": 1,
        "buyerTransactionsCount": 1,
        "hasProfilePage": false,
        "exitDate": null,
        "exitValue": null,
        "exitBuyerName": null,
        "profitLoss": null,
        "holdDays": null
    },
    {
        "id": 10655087,
        "propertyId": 18827922,
        "recordingDate": "2026-01-09",
        "buyerName": "DAVID COLLINS TRUST",
        "formattedBuyerName": "david-collins-trust8d9f7825a50ec7f9bd5d8327ce05f705",
        "lenderName": null,
        "address": "10105 CAMINITO ZAR",
        "phone": null,
        "city": "SAN DIEGO",
        "zipCode": "92126",
        "buildingArea": 1264,
        "yearBuilt": 1975,
        "avmValue": 648700,
        "saleValue": 650000,
        "saleDate": "2026-01-06",
        "sellerName": "BUSHEY BRAD LEE",
        "latitude": 32.90232,
        "longitude": -117.121469,
        "isCorporate": false,
        "isDiscountedPurchase": false,
        "isCashBuyer": true,
        "isPrivateLender": false,
        "bedrooms": 3,
        "bathrooms": 1,
        "propertyType": "Condo",
        "msa": "San Diego-Chula Vista-Carlsbad, CA",
        "state": "CA",
        "loanAmount": 0,
        "buyerPropertiesCount": 1,
        "buyerTransactionsCount": 1,
        "hasProfilePage": false,
        "exitDate": null,
        "exitValue": null,
        "exitBuyerName": null,
        "profitLoss": null,
        "holdDays": null
    },
    {
        "id": 10650036,
        "propertyId": 18953210,
        "recordingDate": "2026-01-09",
        "buyerName": "STAFFORD IS LLC",
        "formattedBuyerName": "stafford-is-llc-ca",
        "lenderName": "CENTER STREET LNDG VIII SPE LL",
        "address": "972 SAPPHIRE ST",
        "phone": null,
        "city": "SAN DIEGO",
        "zipCode": "92109",
        "buildingArea": 1300,
        "yearBuilt": 1987,
        "avmValue": 1361205,
        "saleValue": 1170000,
        "saleDate": "2026-01-07",
        "sellerName": "MECHANIC JONAH",
        "latitude": 32.808732,
        "longitude": -117.255821,
        "isCorporate": true,
        "isDiscountedPurchase": true,
        "isCashBuyer": false,
        "isPrivateLender": true,
        "bedrooms": 3,
        "bathrooms": 2,
        "propertyType": "Condo",
        "msa": "San Diego-Chula Vista-Carlsbad, CA",
        "state": "CA",
        "loanAmount": 1217000,
        "buyerPropertiesCount": 2,
        "buyerTransactionsCount": 3,
        "hasProfilePage": false,
        "exitDate": null,
        "exitValue": null,
        "exitBuyerName": null,
        "profitLoss": null,
        "holdDays": null
    },
    {
        "id": 10650035,
        "propertyId": 18953212,
        "recordingDate": "2026-01-09",
        "buyerName": "STAFFORD IS LLC",
        "formattedBuyerName": "stafford-is-llc-ca",
        "lenderName": "CENTER STREET LNDG VIII SPE LL",
        "address": "976 SAPPHIRE ST",
        "phone": null,
        "city": "SAN DIEGO",
        "zipCode": "92109",
        "buildingArea": 1300,
        "yearBuilt": 1987,
        "avmValue": 1358125,
        "saleValue": 1150000,
        "saleDate": "2026-01-07",
        "sellerName": "MECHANIC JONAH",
        "latitude": 32.808732,
        "longitude": -117.255821,
        "isCorporate": true,
        "isDiscountedPurchase": true,
        "isCashBuyer": false,
        "isPrivateLender": true,
        "bedrooms": 3,
        "bathrooms": 2,
        "propertyType": "Condo",
        "msa": "San Diego-Chula Vista-Carlsbad, CA",
        "state": "CA",
        "loanAmount": 1190000,
        "buyerPropertiesCount": 2,
        "buyerTransactionsCount": 3,
        "hasProfilePage": false,
        "exitDate": null,
        "exitValue": null,
        "exitBuyerName": null,
        "profitLoss": null,
        "holdDays": null
    },
    {
        "id": 10646015,
        "propertyId": 19066366,
        "recordingDate": "2026-01-09",
        "buyerName": "BINNALL-HEDDERMAN MOLLY",
        "formattedBuyerName": "binnall-hedderman-molly1b2d5a344f05525b27a580e85a43c78a",
        "lenderName": null,
        "address": "10325 CAMINITO CUERVO UNIT 185",
        "phone": null,
        "city": "SAN DIEGO",
        "zipCode": "92108",
        "buildingArea": 1103,
        "yearBuilt": 1978,
        "avmValue": 552802,
        "saleValue": 577000,
        "saleDate": "2026-01-09",
        "sellerName": "GRAVES VAN MONTELE",
        "latitude": 32.787256,
        "longitude": -117.112618,
        "isCorporate": false,
        "isDiscountedPurchase": false,
        "isCashBuyer": true,
        "isPrivateLender": false,
        "bedrooms": 2,
        "bathrooms": 2,
        "propertyType": "Condo",
        "msa": "San Diego-Chula Vista-Carlsbad, CA",
        "state": "CA",
        "loanAmount": 0,
        "buyerPropertiesCount": 1,
        "buyerTransactionsCount": 1,
        "hasProfilePage": false,
        "exitDate": null,
        "exitValue": null,
        "exitBuyerName": null,
        "profitLoss": null,
        "holdDays": null
    },
    {
        "id": 10642718,
        "propertyId": 19149225,
        "recordingDate": "2026-01-09",
        "buyerName": "KOTO INDUSTRY LLC",
        "formattedBuyerName": "koto-industry-llc-ca",
        "lenderName": null,
        "address": "7612 HILLSIDE DR",
        "phone": null,
        "city": "LA JOLLA",
        "zipCode": "92037",
        "buildingArea": 3455,
        "yearBuilt": 1987,
        "avmValue": 3483867,
        "saleValue": 3486500,
        "saleDate": "2026-01-07",
        "sellerName": "ROSENBERG LEONARD X",
        "latitude": 32.846253,
        "longitude": -117.257523,
        "isCorporate": true,
        "isDiscountedPurchase": false,
        "isCashBuyer": true,
        "isPrivateLender": false,
        "bedrooms": 3,
        "bathrooms": 3,
        "propertyType": "Single Family Residential",
        "msa": "San Diego-Chula Vista-Carlsbad, CA",
        "state": "CA",
        "loanAmount": 0,
        "buyerPropertiesCount": 2,
        "buyerTransactionsCount": 6,
        "hasProfilePage": true,
        "exitDate": null,
        "exitValue": null,
        "exitBuyerName": null,
        "profitLoss": null,
        "holdDays": null
    },
    {
        "id": 10634230,
        "propertyId": 19412685,
        "recordingDate": "2026-01-09",
        "buyerName": "Opendoor",
        "formattedBuyerName": "opendoor",
        "lenderName": null,
        "address": "2732 CROWN RIDGE RD UNIT 3",
        "phone": null,
        "city": "CHULA VISTA",
        "zipCode": "91915",
        "buildingArea": 1682,
        "yearBuilt": 2004,
        "avmValue": 671672,
        "saleValue": 676000,
        "saleDate": "2026-01-06",
        "sellerName": "JINGCO MARISSA QUILANTANG",
        "latitude": 32.633612,
        "longitude": -116.939774,
        "isCorporate": true,
        "isDiscountedPurchase": false,
        "isCashBuyer": true,
        "isPrivateLender": false,
        "bedrooms": 3,
        "bathrooms": 2,
        "propertyType": "Condo",
        "msa": "San Diego-Chula Vista-Carlsbad, CA",
        "state": "CA",
        "loanAmount": 0,
        "buyerPropertiesCount": 3898,
        "buyerTransactionsCount": 64103,
        "hasProfilePage": true,
        "exitDate": null,
        "exitValue": null,
        "exitBuyerName": null,
        "profitLoss": null,
        "holdDays": null
    },
    {
        "id": 10666620,
        "propertyId": 18496518,
        "recordingDate": "2026-01-07",
        "buyerName": "KANE BARRY",
        "formattedBuyerName": "kane-barryc5fe25e701a76218b6f98cb3c328b615",
        "lenderName": null,
        "address": "3685 VISTA CAMPANA N UNIT 58",
        "phone": null,
        "city": "OCEANSIDE",
        "zipCode": "92057",
        "buildingArea": 1028,
        "yearBuilt": 1965,
        "avmValue": 490496,
        "saleValue": 480000,
        "saleDate": "2026-01-06",
        "sellerName": "NASH ALAN W B",
        "latitude": 33.217591,
        "longitude": -117.329323,
        "isCorporate": false,
        "isDiscountedPurchase": false,
        "isCashBuyer": true,
        "isPrivateLender": false,
        "bedrooms": 2,
        "bathrooms": 2,
        "propertyType": "Single Family Residential",
        "msa": "San Diego-Chula Vista-Carlsbad, CA",
        "state": "CA",
        "loanAmount": 0,
        "buyerPropertiesCount": 1,
        "buyerTransactionsCount": 1,
        "hasProfilePage": false,
        "exitDate": null,
        "exitValue": null,
        "exitBuyerName": null,
        "profitLoss": null,
        "holdDays": null
    },
    {
        "id": 10653845,
        "propertyId": 18859800,
        "recordingDate": "2026-01-07",
        "buyerName": "SARALEGUI ALDO LUCIANO MORE",
        "formattedBuyerName": "saralegui-aldo-luciano-more650-e-san-ysidro-blvd-ste-101",
        "lenderName": null,
        "address": "SHOOTIN IRON TRL",
        "phone": null,
        "city": "JULIAN",
        "zipCode": "92036",
        "buildingArea": 0,
        "yearBuilt": null,
        "avmValue": null,
        "saleValue": 25000,
        "saleDate": "2026-01-07",
        "sellerName": "SCHLIEDER DAVID ALAN",
        "latitude": 32.9763,
        "longitude": -116.4028,
        "isCorporate": false,
        "isDiscountedPurchase": false,
        "isCashBuyer": true,
        "isPrivateLender": false,
        "bedrooms": 0,
        "bathrooms": 0,
        "propertyType": "Vacant Land",
        "msa": "San Diego-Chula Vista-Carlsbad, CA",
        "state": "CA",
        "loanAmount": 0,
        "buyerPropertiesCount": 1,
        "buyerTransactionsCount": 1,
        "hasProfilePage": false,
        "exitDate": null,
        "exitValue": null,
        "exitBuyerName": null,
        "profitLoss": null,
        "holdDays": null
    }
]